license_utils/__init__.py
license_utils/build_licenses.py
license_utils/computation.py
license_utils/matcher.py
license_utils/normalize.py
license_utils/sorensen_dice.py
license_utils-0.0.2.dist-info/LICENSE
license_utils-0.0.2.dist-info/METADATA
license_utils-0.0.2.dist-info/WHEEL
license_utils-0.0.2.dist-info/entry_points.txt
license_utils-0.0.2.dist-info/top_level.txt
license_utils-0.0.2.dist-info/RECORD
