Metadata-Version: 2.1
Name: license-utils
Version: 0.0.2
Summary: Various utilities for working with SPDX / OSS licenses, including a spdx-based license matcher.
Home-page: https://github.com/miweiss/license-utils
Author: Michael Weiss
License: MIT
Keywords: spdx license license-matcher
Classifier: Development Status :: 4 - Beta
Classifier: Programming Language :: Python :: 3
Classifier: License :: OSI Approved :: MIT License
Classifier: Operating System :: OS Independent
License-File: LICENSE
Requires-Dist: aiohttp >=3.8.5
Requires-Dist: requests >=2.31.0
Requires-Dist: nest-asyncio >=1.5.8
Provides-Extra: lint
Requires-Dist: black ==23.3.0 ; extra == 'lint'
Requires-Dist: isort ==5.12.0 ; extra == 'lint'
Requires-Dist: docstr-coverage ==2.2.0 ; extra == 'lint'
Provides-Extra: test
Requires-Dist: pytest ; extra == 'test'
Requires-Dist: pytest-asyncio ; extra == 'test'
